{
  "annotations": {
    "list": [
      {
        "builtIn": 1,
        "datasource": {
          "type": "grafana",
          "uid": "-- Grafana --"
        },
        "enable": true,
        "hide": true,
        "iconColor": "rgba(0, 211, 255, 1)",
        "name": "Annotations & Alerts",
        "type": "dashboard"
      }
    ]
  },
  "description": "using Kafka/Spark",
  "editable": true,
  "fiscalYearStartMonth": 0,
  "graphTooltip": 0,
  "id": 0,
  "links": [],
  "panels": [
    {
      "datasource": {
        "type": "grafana-postgresql-datasource",
        "uid": "afbmzm5ytj0u8c"
      },
      "description": "Shows the number of incoming articles over time. This panel helps verify that the streaming pipeline is active and highlights peaks in news activity.",
      "fieldConfig": {
        "defaults": {
          "color": {
            "fixedColor": "dark-green",
            "mode": "fixed"
          },
          "custom": {
            "axisBorderShow": false,
            "axisCenteredZero": false,
            "axisColorMode": "text",
            "axisLabel": "",
            "axisPlacement": "auto",
            "barAlignment": 0,
            "barWidthFactor": 0.6,
            "drawStyle": "line",
            "fillOpacity": 0,
            "gradientMode": "none",
            "hideFrom": {
              "legend": false,
              "tooltip": false,
              "viz": false
            },
            "insertNulls": false,
            "lineInterpolation": "linear",
            "lineWidth": 3,
            "pointSize": 5,
            "scaleDistribution": {
              "type": "linear"
            },
            "showPoints": "auto",
            "showValues": false,
            "spanNulls": false,
            "stacking": {
              "group": "A",
              "mode": "none"
            },
            "thresholdsStyle": {
              "mode": "off"
            }
          },
          "mappings": [],
          "thresholds": {
            "mode": "absolute",
            "steps": [
              {
                "color": "green",
                "value": 0
              },
              {
                "color": "red",
                "value": 80
              }
            ]
          }
        },
        "overrides": []
      },
      "gridPos": {
        "h": 6,
        "w": 8,
        "x": 0,
        "y": 0
      },
      "id": 1,
      "options": {
        "legend": {
          "calcs": [],
          "displayMode": "list",
          "placement": "bottom",
          "showLegend": true
        },
        "tooltip": {
          "hideZeros": false,
          "mode": "single",
          "sort": "none"
        }
      },
      "pluginVersion": "12.3.2",
      "targets": [
        {
          "dataset": "streaming",
          "datasource": {
            "type": "grafana-postgresql-datasource",
            "uid": "afbmzm5ytj0u8c"
          },
          "editorMode": "code",
          "format": "table",
          "rawQuery": true,
          "rawSql": "SELECT\r\n  date_trunc('minute', event_time) AS time,\r\n  COUNT(*) AS articles\r\nFROM articles_enriched\r\nGROUP BY time\r\nORDER BY time;\r\n",
          "refId": "A",
          "sql": {
            "columns": [
              {
                "parameters": [],
                "type": "function"
              }
            ],
            "groupBy": [
              {
                "property": {
                  "type": "string"
                },
                "type": "groupBy"
              }
            ],
            "limit": 50
          }
        }
      ],
      "title": "Article Volume per minute",
      "type": "timeseries"
    },
    {
      "datasource": {
        "type": "grafana-postgresql-datasource",
        "uid": "afbmzm5ytj0u8c"
      },
      "description": "Displays the evolution of positive, negative, and neutral sentiments over time. Useful to observe how public tone changes in response to events.",
      "fieldConfig": {
        "defaults": {
          "color": {
            "fixedColor": "semi-dark-blue",
            "mode": "shades"
          },
          "custom": {
            "axisBorderShow": false,
            "axisCenteredZero": false,
            "axisColorMode": "text",
            "axisLabel": "",
            "axisPlacement": "auto",
            "fillOpacity": 80,
            "gradientMode": "none",
            "hideFrom": {
              "legend": false,
              "tooltip": false,
              "viz": false
            },
            "lineWidth": 3,
            "scaleDistribution": {
              "type": "linear"
            },
            "thresholdsStyle": {
              "mode": "off"
            }
          },
          "mappings": [],
          "thresholds": {
            "mode": "absolute",
            "steps": [
              {
                "color": "green",
                "value": 0
              },
              {
                "color": "red",
                "value": 80
              }
            ]
          }
        },
        "overrides": [
          {
            "matcher": {
              "id": "byName",
              "options": "neutral"
            },
            "properties": [
              {
                "id": "color",
                "value": {
                  "fixedColor": "orange",
                  "mode": "fixed"
                }
              }
            ]
          },
          {
            "matcher": {
              "id": "byName",
              "options": "negative"
            },
            "properties": [
              {
                "id": "color",
                "value": {
                  "fixedColor": "red",
                  "mode": "fixed"
                }
              }
            ]
          },
          {
            "matcher": {
              "id": "byName",
              "options": "positive"
            },
            "properties": [
              {
                "id": "color",
                "value": {
                  "fixedColor": "dark-green",
                  "mode": "fixed"
                }
              }
            ]
          }
        ]
      },
      "gridPos": {
        "h": 7,
        "w": 16,
        "x": 8,
        "y": 0
      },
      "id": 2,
      "options": {
        "barRadius": 0.3,
        "barWidth": 0.59,
        "colorByField": "Time",
        "fullHighlight": false,
        "groupWidth": 0.7,
        "legend": {
          "calcs": [],
          "displayMode": "table",
          "placement": "right",
          "showLegend": true
        },
        "orientation": "vertical",
        "showValue": "never",
        "stacking": "normal",
        "text": {},
        "tooltip": {
          "hideZeros": false,
          "mode": "single",
          "sort": "none"
        },
        "xField": "Time",
        "xTickLabelRotation": 0,
        "xTickLabelSpacing": 0
      },
      "pluginVersion": "12.3.2",
      "targets": [
        {
          "dataset": "streaming",
          "editorMode": "code",
          "format": "table",
          "rawQuery": true,
          "rawSql": "SELECT\r\n  date_trunc('hour', event_time) AS time,\r\n  sentiment,\r\n  COUNT(*) AS count\r\nFROM\r\n  articles_enriched\r\nGROUP BY\r\n  time,\r\n  sentiment\r\nORDER BY\r\n  time;",
          "refId": "A",
          "sql": {
            "columns": [
              {
                "parameters": [],
                "type": "function"
              }
            ],
            "groupBy": [
              {
                "property": {
                  "type": "string"
                },
                "type": "groupBy"
              }
            ],
            "limit": 50
          }
        }
      ],
      "title": "Sentiment Trend",
      "transformations": [
        {
          "id": "groupingToMatrix",
          "options": {
            "columnField": "sentiment",
            "rowField": "time",
            "valueField": "count"
          }
        },
        {
          "id": "sortBy",
          "options": {
            "fields": {},
            "sort": [
              {
                "desc": false,
                "field": "time\\sentiment"
              }
            ]
          }
        }
      ],
      "type": "barchart"
    },
    {
      "datasource": {
        "type": "grafana-postgresql-datasource",
        "uid": "afbmzm5ytj0u8c"
      },
      "description": "Breaks down sentiment counts per news source. Allows comparison of how different media outlets frame topics emotionally.",
      "fieldConfig": {
        "defaults": {
          "color": {
            "mode": "thresholds"
          },
          "custom": {
            "align": "auto",
            "cellOptions": {
              "type": "auto"
            },
            "footer": {
              "reducers": []
            },
            "inspect": false
          },
          "mappings": [],
          "thresholds": {
            "mode": "absolute",
            "steps": [
              {
                "color": "green",
                "value": 0
              },
              {
                "color": "red",
                "value": 80
              }
            ]
          }
        },
        "overrides": [
          {
            "matcher": {
              "id": "byName",
              "options": "Sentiment"
            },
            "properties": [
              {
                "id": "custom.width",
                "value": 90
              }
            ]
          },
          {
            "matcher": {
              "id": "byName",
              "options": "Source"
            },
            "properties": [
              {
                "id": "custom.width",
                "value": 179
              }
            ]
          },
          {
            "matcher": {
              "id": "byName",
              "options": "Articles"
            },
            "properties": [
              {
                "id": "custom.width",
                "value": 75
              }
            ]
          }
        ]
      },
      "gridPos": {
        "h": 10,
        "w": 8,
        "x": 0,
        "y": 6
      },
      "id": 6,
      "options": {
        "cellHeight": "sm",
        "showHeader": true
      },
      "pluginVersion": "12.3.2",
      "targets": [
        {
          "dataset": "streaming",
          "editorMode": "code",
          "format": "table",
          "rawQuery": true,
          "rawSql": "SELECT\r\n  source,\r\n  sentiment,\r\n  COUNT(*) AS count\r\nFROM articles_enriched\r\nGROUP BY source, sentiment\r\nORDER BY source, count DESC;\r\n",
          "refId": "A",
          "sql": {
            "columns": [
              {
                "parameters": [],
                "type": "function"
              }
            ],
            "groupBy": [
              {
                "property": {
                  "type": "string"
                },
                "type": "groupBy"
              }
            ],
            "limit": 50
          }
        }
      ],
      "title": "Sentiment by Source",
      "transformations": [
        {
          "id": "organize",
          "options": {
            "excludeByName": {},
            "includeByName": {},
            "indexByName": {},
            "renameByName": {
              "count": "Articles",
              "sentiment": "Sentiment",
              "source": "Source"
            }
          }
        }
      ],
      "type": "table"
    },
    {
      "datasource": {
        "type": "grafana-postgresql-datasource",
        "uid": "afbmzm5ytj0u8c"
      },
      "description": "Represents the global distribution of sentiments across all processed articles. Provides a high-level overview of the general tone of the news stream.",
      "fieldConfig": {
        "defaults": {
          "color": {
            "fixedColor": "semi-dark-purple",
            "mode": "palette-classic"
          },
          "custom": {
            "hideFrom": {
              "legend": false,
              "tooltip": false,
              "viz": false
            }
          },
          "mappings": []
        },
        "overrides": []
      },
      "gridPos": {
        "h": 9,
        "w": 6,
        "x": 8,
        "y": 7
      },
      "id": 3,
      "options": {
        "legend": {
          "displayMode": "table",
          "placement": "right",
          "showLegend": true,
          "values": [
            "value"
          ]
        },
        "pieType": "pie",
        "reduceOptions": {
          "calcs": [
            "sum"
          ],
          "fields": "/^count$/",
          "values": true
        },
        "sort": "desc",
        "tooltip": {
          "hideZeros": false,
          "mode": "single",
          "sort": "none"
        }
      },
      "pluginVersion": "12.3.2",
      "targets": [
        {
          "dataset": "streaming",
          "editorMode": "code",
          "format": "table",
          "rawQuery": true,
          "rawSql": "SELECT\r\n  sentiment,\r\n  COUNT(*) AS count\r\nFROM articles_enriched\r\nGROUP BY sentiment;\r\n",
          "refId": "A",
          "sql": {
            "columns": [
              {
                "parameters": [],
                "type": "function"
              }
            ],
            "groupBy": [
              {
                "property": {
                  "type": "string"
                },
                "type": "groupBy"
              }
            ],
            "limit": 50
          }
        }
      ],
      "title": "Overall Sentiment Distribution",
      "transformations": [
        {
          "id": "labelsToFields",
          "options": {
            "mode": "columns"
          }
        }
      ],
      "type": "piechart"
    },
    {
      "datasource": {
        "type": "grafana-postgresql-datasource",
        "uid": "afbmzm5ytj0u8c"
      },
      "description": "Displays the distribution of detected languages in the incoming articles. Useful for understanding the linguistic diversity of the data stream.",
      "fieldConfig": {
        "defaults": {
          "color": {
            "fixedColor": "super-light-orange",
            "mode": "fixed"
          },
          "custom": {
            "axisBorderShow": false,
            "axisCenteredZero": false,
            "axisColorMode": "text",
            "axisLabel": "",
            "axisPlacement": "auto",
            "fillOpacity": 80,
            "gradientMode": "none",
            "hideFrom": {
              "legend": false,
              "tooltip": false,
              "viz": false
            },
            "lineWidth": 1,
            "scaleDistribution": {
              "type": "linear"
            },
            "thresholdsStyle": {
              "mode": "off"
            }
          },
          "mappings": [],
          "thresholds": {
            "mode": "absolute",
            "steps": [
              {
                "color": "green",
                "value": 0
              },
              {
                "color": "red",
                "value": 80
              }
            ]
          }
        },
        "overrides": []
      },
      "gridPos": {
        "h": 9,
        "w": 10,
        "x": 14,
        "y": 7
      },
      "id": 5,
      "options": {
        "barRadius": 0,
        "barWidth": 0.97,
        "fullHighlight": false,
        "groupWidth": 0.7,
        "legend": {
          "calcs": [],
          "displayMode": "list",
          "placement": "bottom",
          "showLegend": true
        },
        "orientation": "auto",
        "showValue": "auto",
        "stacking": "none",
        "tooltip": {
          "hideZeros": false,
          "mode": "single",
          "sort": "none"
        },
        "xTickLabelRotation": 0,
        "xTickLabelSpacing": 0
      },
      "pluginVersion": "12.3.2",
      "targets": [
        {
          "dataset": "streaming",
          "editorMode": "code",
          "format": "table",
          "rawQuery": true,
          "rawSql": "SELECT\r\n  detected_lang,\r\n  COUNT(*) AS count\r\nFROM articles_enriched\r\nGROUP BY detected_lang\r\nORDER BY count DESC\r\nLIMIT 15;\r\n",
          "refId": "A",
          "sql": {
            "columns": [
              {
                "parameters": [],
                "type": "function"
              }
            ],
            "groupBy": [
              {
                "property": {
                  "type": "string"
                },
                "type": "groupBy"
              }
            ],
            "limit": 50
          }
        }
      ],
      "title": "Language Distribution",
      "type": "barchart"
    },
    {
      "datasource": {
        "type": "grafana-postgresql-datasource",
        "uid": "afbmzm5ytj0u8c"
      },
      "description": "Shows the most active news sources based on the number of published articles. Helps identify which media outlets contribute the most content.",
      "fieldConfig": {
        "defaults": {
          "color": {
            "fixedColor": "light-orange",
            "mode": "fixed"
          },
          "mappings": [],
          "thresholds": {
            "mode": "absolute",
            "steps": [
              {
                "color": "green",
                "value": 0
              },
              {
                "color": "red",
                "value": 80
              }
            ]
          }
        },
        "overrides": []
      },
      "gridPos": {
        "h": 12,
        "w": 24,
        "x": 0,
        "y": 16
      },
      "id": 4,
      "options": {
        "colorByField": "value",
        "groupByField": "source",
        "labelFields": [],
        "sizeField": "value",
        "textField": "label",
        "tiling": "treemapSquarify"
      },
      "pluginVersion": "2.1.1",
      "targets": [
        {
          "dataset": "streaming",
          "editorMode": "code",
          "format": "table",
          "rawQuery": true,
          "rawSql": "SELECT\r\n  source AS label,\r\n  COUNT(*) AS value\r\nFROM articles_enriched\r\nGROUP BY source\r\nORDER BY value DESC\r\nLIMIT 20;\r\n\r\n",
          "refId": "A",
          "sql": {
            "columns": [
              {
                "parameters": [],
                "type": "function"
              }
            ],
            "groupBy": [
              {
                "property": {
                  "type": "string"
                },
                "type": "groupBy"
              }
            ],
            "limit": 50
          }
        }
      ],
      "title": "Top sources",
      "type": "marcusolsson-treemap-panel"
    }
  ],
  "preload": false,
  "schemaVersion": 42,
  "tags": [],
  "templating": {
    "list": []
  },
  "time": {
    "from": "now-24h",
    "to": "now"
  },
  "timepicker": {},
  "timezone": "browser",
  "title": "Streaming News Analytics",
  "uid": "admpg2z",
  "version": 24
}